{
  "frame": {
    "name": "Be a Celorian",
    "version": "1",
    "iconUrl": "https://be-a-celorian.vercel.app/img/logo-64px.png",
    "homeUrl": "https://be-a-celorian.vercel.app",
    "imageUrl": "https://be-a-celorian.vercel.app/img/image.png",
    "splashImageUrl": "https://be-a-celorian.vercel.app/img/splash.png",
    "splashBackgroundColor": "#000000",
    "webhookUrl": "https://be-a-celorian.vercel.app/api/webhook",
    "subtitle": "Miniapp for explore Celo Eco",
    "description": "Miniapp for explore Celo Eco",
    "primaryCategory": "social",
    "screenshotUrls": [
      "https://be-a-celorian.vercel.app/img/screenshot.png"
    ]
  },
  "accountAssociation": {
    "header": "eyJmaWQiOjI2MDI5OSwidHlwZSI6ImF1dGgiLCJrZXkiOiIweGE1NjNDYTRFMGZmMjIzNjMzMkUyRkRmRDkxZkZEOTZlNTk0NzQ5RkYifQ",
    "payload": "eyJkb21haW4iOiJiZS1hLWNlbG9yaWFuLnZlcmNlbC5hcHAifQ",
    "signature": "07d7ZZHq3ETg/3H1LadtROOtVq0BnwBeAyt/a52qKRA+XHq4PCt6MzhMo3VpVAUpBQzJqGwpnwDs8/1FrgFB/xs="
  }
}